README.md
setup.cfg
setup.py
benchmark_for_transformers/__init__.py
benchmark_for_transformers/benchmark.py
benchmark_for_transformers/metrics_utils.py
benchmark_for_transformers/model.py
benchmark_for_transformers/run_cli.py
benchmark_for_transformers.egg-info/PKG-INFO
benchmark_for_transformers.egg-info/SOURCES.txt
benchmark_for_transformers.egg-info/dependency_links.txt
benchmark_for_transformers.egg-info/entry_points.txt
benchmark_for_transformers.egg-info/requires.txt
benchmark_for_transformers.egg-info/top_level.txt
benchmark_for_transformers/models/__init__.py
benchmark_for_transformers/models/classification.py
benchmark_for_transformers/models/ner.py
benchmark_for_transformers/models/ordering.py
benchmark_for_transformers/models/summarization.py